octodb/__init__.py
octodb/_sqlite3.cpython-310-darwin.so
octodb/dbapi2.py
octodb-0.4.11.dist-info/LICENSE
octodb-0.4.11.dist-info/METADATA
octodb-0.4.11.dist-info/WHEEL
octodb-0.4.11.dist-info/top_level.txt
octodb-0.4.11.dist-info/RECORD
