Metadata-Version: 2.1
Name: octodb
Version: 0.4.11
Summary: DB-API 2.0 interface for OctoDB
Home-page: https://gitlab.com/octodb/octodb-python3
Author: Bernardo Ramos
Author-email: contact@octodb.io
License: zlib/libpng
Platform: ALL
Classifier: Development Status :: 4 - Beta
Classifier: Intended Audience :: Developers
Classifier: License :: OSI Approved :: zlib/libpng License
Classifier: Operating System :: MacOS :: MacOS X
Classifier: Operating System :: Microsoft :: Windows
Classifier: Operating System :: POSIX
Classifier: Programming Language :: C
Classifier: Programming Language :: Python
Classifier: Topic :: Database :: Database Engines/Servers
Classifier: Topic :: Software Development :: Libraries :: Python Modules
License-File: LICENSE
